import_analyzer/__init__.py
import_analyzer/__main__.py
import_analyzer/_ast_helpers.py
import_analyzer/_autofix.py
import_analyzer/_cross_file.py
import_analyzer/_data.py
import_analyzer/_detection.py
import_analyzer/_format.py
import_analyzer/_graph.py
import_analyzer/_main.py
import_analyzer/_resolution.py
import_analyzer/py.typed
import_analyzer_py-0.1.5.dist-info/licenses/LICENSE
import_analyzer_py-0.1.5.dist-info/METADATA
import_analyzer_py-0.1.5.dist-info/WHEEL
import_analyzer_py-0.1.5.dist-info/entry_points.txt
import_analyzer_py-0.1.5.dist-info/top_level.txt
import_analyzer_py-0.1.5.dist-info/RECORD
