Metadata-Version: 2.4
Name: import-analyzer-py
Version: 0.1.5
Summary: A Python import analyzer with cross-file analysis, unused import detection, and autofix
License-Expression: MIT
Project-URL: Homepage, https://github.com/cmyui/import-analyzer-py
Project-URL: Repository, https://github.com/cmyui/import-analyzer-py
Project-URL: Issues, https://github.com/cmyui/import-analyzer-py/issues
Keywords: imports,linter,unused,autofix,static-analysis
Classifier: Development Status :: 4 - Beta
Classifier: Environment :: Console
Classifier: Intended Audience :: Developers
Classifier: Operating System :: OS Independent
Classifier: Programming Language :: Python
Classifier: Programming Language :: Python :: 3
Classifier: Programming Language :: Python :: 3 :: Only
Classifier: Programming Language :: Python :: 3.10
Classifier: Programming Language :: Python :: 3.11
Classifier: Programming Language :: Python :: 3.12
Classifier: Programming Language :: Python :: 3.13
Classifier: Programming Language :: Python :: 3.14
Classifier: Topic :: Software Development :: Quality Assurance
Classifier: Typing :: Typed
Requires-Python: >=3.10
License-File: LICENSE
Provides-Extra: dev
Requires-Dist: pytest>=7.0; extra == "dev"
Requires-Dist: coverage[toml]>=7.0; extra == "dev"
Requires-Dist: covdefaults>=2.3; extra == "dev"
Dynamic: license-file
